flask_sandboy
