Metadata-Version: 1.1
Name: flask-sandboy
Version: 0.0.2.6
Summary: Automated REST APIs for SQLAlchemy models
Home-page: http://github.com/jeffknupp/flask_sandboy/
Author: Jeff Knupp
Author-email: jeff@jeffknupp.com
License: BSD License
Platform: any
Classifier: Programming Language :: Python
Classifier: Programming Language :: Python :: 2
Classifier: Programming Language :: Python :: 3
Classifier: Development Status :: 4 - Beta
Classifier: Natural Language :: English
Classifier: Environment :: Web Environment
Classifier: Intended Audience :: Developers
Classifier: License :: OSI Approved :: BSD License
Classifier: Operating System :: OS Independent
Classifier: Topic :: Software Development :: Libraries :: Python Modules
Classifier: Topic :: Software Development :: Libraries :: Application Frameworks
Classifier: Topic :: Internet :: WWW/HTTP :: Dynamic Content
